pkgdownloader/__init__.py
pkgdownloader/docker/.gitkeep
pkgdownloader/downloader.py
pkgdownloader/pkgdownloader.py
pkgdownloader/templates/DOCKERFILE-deb.jinja
pkgdownloader/templates/DOCKERFILE-rpm.jinja
pkgdownloader/templates.py
pkg_downloader-0.1.4.dist-info/entry_points.txt
pkg_downloader-0.1.4.dist-info/LICENSE
pkg_downloader-0.1.4.dist-info/WHEEL
pkg_downloader-0.1.4.dist-info/METADATA
pkg_downloader-0.1.4.dist-info/RECORD
