Metadata-Version: 2.1
Name: pkg-downloader
Version: 0.1.4
Summary: A streamlined way to download packages for offline installation.
Home-page: https://github.com/TheComputerDan/pkg-downloader
License: MIT
Author: TheComputerDan
Author-email: thedoctordan@outlook.com
Requires-Python: >=3.7,<4.0
Classifier: Development Status :: 2 - Pre-Alpha
Classifier: License :: OSI Approved :: MIT License
Classifier: Programming Language :: Python :: 3
Classifier: Programming Language :: Python :: 3.7
Classifier: Programming Language :: Python :: 3.8
Classifier: Programming Language :: Python :: 3.9
Requires-Dist: Jinja2 (>=2.11.2,<3.0.0)
Requires-Dist: docker (>=4.3.1,<5.0.0)
Project-URL: Repository, https://github.com/TheComputerDan/pkg-downloader
